sites_faciles/Aptfile
sites_faciles/Dockerfile
sites_faciles/Makefile
sites_faciles/Procfile
sites_faciles/__init__.py
sites_faciles/apps.py
sites_faciles/cron.json.example
sites_faciles/docker-compose.yml
sites_faciles/entrypoint.sh
sites_faciles/justfile
sites_faciles/manage.py
sites_faciles/blog/__init__.py
sites_faciles/blog/admin.py
sites_faciles/blog/apps.py
sites_faciles/blog/blocks.py
sites_faciles/blog/managers.py
sites_faciles/blog/models.py
sites_faciles/blog/utils.py
sites_faciles/blog/views.py
sites_faciles/blog/locale/fr/LC_MESSAGES/django.mo
sites_faciles/blog/locale/fr/LC_MESSAGES/django.po
sites_faciles/blog/migrations/0001_initial.py
sites_faciles/blog/migrations/0002_alter_blogentrypage_body_alter_blogindexpage_body.py
sites_faciles/blog/migrations/0003_blogentrypage_header_color_class_and_more.py
sites_faciles/blog/migrations/0004_alter_blogentrypage_body_alter_blogindexpage_body.py
sites_faciles/blog/migrations/0005_delete_tag_blogentrypage_header_cta_text_and_more.py
sites_faciles/blog/migrations/0006_category_colophon_alter_blogentrypage_body_and_more.py
sites_faciles/blog/migrations/0007_alter_blogentrypage_body_and_more.py
sites_faciles/blog/migrations/0008_alter_blogentrypage_body_alter_blogindexpage_body_and_more.py
sites_faciles/blog/migrations/0009_alter_blogentrypage_body_alter_blogindexpage_body_and_more.py
sites_faciles/blog/migrations/0010_alter_blogentrypage_body_alter_blogindexpage_body_and_more.py
sites_faciles/blog/migrations/0011_alter_blogentrypage_body_alter_blogindexpage_body_and_more.py
sites_faciles/blog/migrations/0012_alter_blogentrypage_body_alter_blogindexpage_body_and_more.py
sites_faciles/blog/migrations/0013_alter_blogentrypage_body_alter_blogindexpage_body_and_more.py
sites_faciles/blog/migrations/0014_alter_blogentrypage_body_alter_blogindexpage_body_and_more.py
sites_faciles/blog/migrations/0015_alter_blogentrypage_body_alter_blogindexpage_body.py
sites_faciles_experiment-1.13.0.dist-info/licenses/LICENSE
sites_faciles_experiment-1.13.0.dist-info/WHEEL
sites_faciles_experiment-1.13.0.dist-info/METADATA
sites_faciles_experiment-1.13.0.dist-info/RECORD
