Metadata-Version: 2.4
Name: sites-faciles-experiment
Version: 1.13.0
Summary: Gestionnaire de contenu permettant de créer et gérer un site internet basé sur le Système de design de l’État, accessible et responsive
Author-email: Sébastien Reuiller <sebastien.reuiller@beta.gouv.fr>, Sylvain Boissel <sylvain.boissel@beta.gouv.fr>
Maintainer-email: Sylvain Boissel <sylvain.boissel@beta.gouv.fr>
Requires-Python: <4.0,>=3.10
License-File: LICENSE
Requires-Dist: django<6.0.0,>=5.1.4
Requires-Dist: wagtail<7.0,>=6.1
Requires-Dist: django-dsfr (>=2.1.0,<3.0.0)
Requires-Dist: psycopg2-binary<3.0.0,>=2.9.9
Requires-Dist: python-dotenv<2.0.0,>=1.0.0
Requires-Dist: dj-database-url<3.0.0,>=2.1.0
Requires-Dist: gunicorn<23.0.0,>=22.0.0
Requires-Dist: django-sass-processor<2.0,>=1.3
Requires-Dist: libsass<1.0.0,>=0.22.0
Requires-Dist: dj-static<1.0.0,>=0.0.6
Requires-Dist: wagtailmenus<5.0,>=4.0
Requires-Dist: wagtail-modeladmin<3.0.0,>=2.0.0
Requires-Dist: wagtail-markdown<1.0.0,>=0.11.1
Requires-Dist: unidecode<2.0.0,>=1.3.8
Requires-Dist: django-storages[s3]<2.0.0,>=1.14.2
Requires-Dist: boto3==1.35.99
Requires-Dist: beautifulsoup4<5.0.0,>=4.12.3
Requires-Dist: django-taggit<6.0.0,>=5.0.1
Requires-Dist: wagtail-localize<2.0,>=1.9
Requires-Dist: icalendar<6.0.0,>=5.0.13
Requires-Dist: faker<25.0.0,>=24.3.0
Requires-Dist: rust-just (>=1.39.0,<2.0.0)
